{
  "source_file": "DEFS/POWERS/V_PARAGONPOLICE_GRENADE_LAUNCHER.POWERSETS",
  "display_name": "Grenade_Launcher",
  "display_help": "Paragon Police",
  "display_short_help": "Paragon Police",
  "icon_name": "Grenade_Launcher_set.ico",
  "powers": [
    "V_ParagonPolice.Grenade_Launcher.Grenade",
    "V_ParagonPolice.Grenade_Launcher.Heavy_Grenade",
    "V_ParagonPolice.Grenade_Launcher.Incendiary_Grenade",
    "V_ParagonPolice.Grenade_Launcher.Smoke_Grenade"
  ],
  "available": [
    0,
    0,
    0,
    0
  ],
  "aimax_level": [
    0,
    0,
    0,
    0
  ],
  "aimin_rank_con": [
    4294957297,
    4294957297,
    4294957297,
    4294957297
  ],
  "aimax_rank_con": [
    9999,
    9999,
    9999,
    9999
  ],
  "min_difficulty": [
    2,
    2,
    2,
    2
  ],
  "max_difficulty": [
    9999,
    9999,
    9999,
    9999
  ]
}