{
  "Warmth_of_Prometheus": {
    "crcfull_name": 3874898589,
    "source_file": "DEFS/POWERS/OBJECTS_WARMTH_OF_PROMETHEUS.POWERS",
    "source_name": "Objects.Warmth_of_Prometheus.Warmth_of_Prometheus",
    "display_name": "Warmth of Prometheus",
    "display_help": "Prometheus is extending a boon over your group to assist your drive to face the Incarnate Trials. This confers a small boost to damage, recharge, and healing.",
    "display_short_help": "+DMG, +Rech, +Heal",
    "icon_name": "Incarnate_StoryArc.tga",
    "type": 1,
    "shoot_through_untouchable": true,
    "ai_report": 1,
    "effect_area": 7,
    "activate_period": 10,
    "target_visibility": 1,
    "ents_auto_hit": [
      16
    ],
    "ents_affected": [
      16
    ],
    "effects": [
      {
        "attrib_mod": [
          {
            "attrib": [
              28,
              0,
              4,
              8,
              12,
              16,
              20,
              24,
              36,
              356
            ],
            "aspect": 16,
            "table": "Ranged_Ones",
            "scale": 0.075,
            "duration": 10.25,
            "stack_type": 3,
            "flags": [
              112,
              0
            ]
          }
        ]
      }
    ],
    "is_environment_hit": true,
    "attrib_cache": [
      0,
      4,
      8,
      12,
      16,
      20,
      24,
      28,
      36,
      356
    ]
  }
}