{
  "crcfull_name": 733615773,
  "source_file": "DEFS/POWERS/MISSION_MAKER_SECONDARY_ICE_MELEE.POWERS",
  "source_name": "Mission_Maker_Secondary.Ice_Melee.Ice_Sword",
  "display_name": "Ice Sword",
  "display_help": "You create a blade of solid ice that deals good damage. Being hit by this Ice Sword will Slow a target's movement and attack speed, due to the intense chill. Damage: Moderate, Recharge: Moderate",
  "display_short_help": "Melee, Moderate DMG(Cold/Lethal), Foe -Recharge, -SPD",
  "display_target_help": "You are chilled. Your Attack speed and Running speed are reduced.",
  "display_target_short_help": "-Recharge, -SPD",
  "icon_name": "IcyOnslaught_IceSword.tga",
  "attack_types": [
    "Melee",
    "Lethal",
    "Cold"
  ],
  "buy_requires": [
    "Mission_Maker_Attacks.Ice_Melee.Frozen_Fists",
    "Mission_Maker_Attacks.Ice_Melee.Ice_Sword",
    "||",
    "!"
  ],
  "range": 5,
  "time_to_activate": 1.33,
  "recharge_time": 6,
  "endurance_cost": 9.24,
  "target": 19,
  "effects": [
    {
      "attrib_mod": [
        {
          "attrib": [
            4
          ],
          "aspect": 32,
          "table": "Melee_TempDamage",
          "scale": 0.5
        },
        {
          "attrib": [
            12
          ],
          "aspect": 32,
          "table": "Melee_TempDamage",
          "scale": 0.82
        },
        {
          "attrib": [
            188,
            192,
            200
          ],
          "table": "Melee_Slow",
          "scale": 0.1,
          "duration": 8
        },
        {
          "attrib": [
            204,
            356
          ],
          "aspect": 16,
          "table": "Melee_Slow",
          "scale": 0.1,
          "duration": 8,
          "flags": [
            656,
            0
          ]
        }
      ]
    }
  ],
  "strengths_disallowed": [
    348
  ],
  "proc_main_target_only": true,
  "anim_main_target_only": true,
  "preference_multiplier": 6,
  "dont_set_stance": true,
  "point_value": 60
}