{
  "crcfull_name": 2750938702,
  "source_file": "DEFS/POWERS/V_FREEDOMPHALANX_STATESMAN.POWERS",
  "source_name": "V_FreedomPhalanx.Statesman.Punch",
  "display_name": "Punch",
  "display_help": "Your Super Strength Punch can deal a moderate amount of damage, but most of all can knock your opponent off his feet, unable to attack again until he stands up. Damage: Moderate, Recharge: Fast",
  "display_short_help": "Melee, Moderate DMG(Smash), Knockback",
  "display_target_help": "Your Super Strength Punch can deal a moderate amount of damage, but most of all can knock your opponent off his feet, unable to attack again until he stands up. Damage: Moderate, Recharge: Fast",
  "display_target_short_help": "Melee, Moderate DMG(Smash), Knockback",
  "icon_name": "SuperStrength_Punch.tga",
  "attack_types": [
    "Melee",
    "Smashing"
  ],
  "range": 5,
  "time_to_activate": 1.2,
  "recharge_time": 10,
  "endurance_cost": 7,
  "target": 19,
  "effects": [
    {
      "attrib_mod": [
        {
          "attrib": [
            0
          ],
          "aspect": 32,
          "table": "Melee_Damage",
          "scale": 1.3
        }
      ]
    },
    {
      "chance": 0.9,
      "attrib_mod": [
        {
          "attrib": [
            328
          ],
          "scale": 0.67
        }
      ]
    }
  ]
}