{
  "crcfull_name": 1615559486,
  "source_file": "DEFS/POWERS/MASTERMIND_PETS_MEDIC_3.POWERS",
  "source_name": "Mastermind_Pets.Medic_3.Stimulant",
  "display_name": "Stimulant",
  "display_help": "Frees an ally from any Immobilization, Sleep, Disorient, Hold, Fear or Confuse effects and leaves them resistant to such effects for a brief time. Protection will improve with Multiple applications and as you advance in level. This power is interruptible and shouldn't be used in the heat of combat.",
  "display_short_help": "Close, Ally Res(Disorient, Hold, Immobilize, Sleep, Fear, Confuse)",
  "display_target_help": "The Stimulant provides some resistance to Immobilization, Sleep, Disorient, Hold, Fear or Confuse effects.",
  "display_target_short_help": "Res(Disorient, Hold, Immobilize, Sleep, Fear, Confuse)",
  "display_attacker_hit": "{PlayerSource} uses their {PowerName} to protect {PlayerDest} from Immobilization, Sleep, Disorient, Hold, Fear or Confuse effects.",
  "display_victim_hit": "{PlayerSource} protects you from IImmobilization, Sleep, Disorient, Hold, Fear or Confuse effects with a Stimulant.",
  "icon_name": "Medicine_Stimulant.tga",
  "range": 25,
  "time_to_activate": 3.17,
  "recharge_time": 15,
  "endurance_cost": 10.4,
  "target": 16,
  "ents_auto_hit": [
    16
  ],
  "ents_affected": [
    16
  ],
  "boosts_allowed": [
    23
  ],
  "modes_disallowed": [
    12
  ],
  "ai_groups": [
    "kBuff"
  ],
  "effects": [
    {
      "attrib_mod": [
        {
          "attrib": [
            256,
            264,
            268,
            272,
            276,
            280
          ],
          "table": "Ranged_Res_Boolean",
          "scale": -20,
          "duration": 45,
          "flags": [
            544,
            0
          ]
        }
      ]
    }
  ],
  "strengths_disallowed": [
    356
  ],
  "cancelable": true
}