{
  "crcfull_name": 1234332218,
  "source_file": "DEFS/POWERS/STALKER_MELEE_SPINES.POWERS",
  "source_name": "Stalker_Melee.Spines.Ripper",
  "display_name": "Ripper",
  "display_help": "You can unleash a spectacular slashing maneuver that attacks all foes in a wide arc in front of you. Ripper deals massive lethal damage and poisons multiple targets. It can even knock foes down. Spine poison Slows affected targets and deals additional Toxic damage. If executed while hidden, all affected targets have a chance to be hit with a Critical Hit for extra damage. Damage: High, Recharge: Slow",
  "display_short_help": "Melee (Cone), High DMG(Lethal), DoT(Toxic), Knockback, -SPD, -Recharge",
  "display_target_help": "You are poisoned! Your Attack speed and Running speed are reduced.",
  "display_target_short_help": "DoT(Toxic), -Recharge, -SPD",
  "icon_name": "Quills_BoneSword.tga",
  "attack_types": [
    "Melee",
    "Lethal"
  ],
  "effect_area": 1,
  "max_targets_hit": 5,
  "radius": 7,
  "arc": 1.5707964,
  "range": 7,
  "time_to_activate": 2.17,
  "recharge_time": 11,
  "endurance_cost": 11.024,
  "target": 19,
  "boosts_allowed": [
    29,
    23,
    18,
    17,
    9,
    5
  ],
  "modes_disallowed": [
    12
  ],
  "effects": [
    {
      "requires": [
        "enttype",
        "target>",
        "critter",
        "eq"
      ],
      "attrib_mod": [
        {
          "attrib": [
            4
          ],
          "aspect": 32,
          "table": "Melee_Damage",
          "scale": 1.7
        },
        {
          "attrib": [
            36
          ],
          "aspect": 32,
          "table": "Melee_Damage",
          "scale": 0.2,
          "duration": 4.1,
          "delay": 0.5,
          "period": 1,
          "tick_chance": 0.8,
          "flags": [
            644,
            0
          ]
        },
        {
          "attrib": [
            328
          ],
          "scale": 0.67
        }
      ]
    },
    {
      "chance": 0.1,
      "requires": [
        "kMeter",
        "source>",
        ".9",
        "<",
        "kHeld",
        "target>",
        "0",
        ">",
        "kSleep",
        "target>",
        "0",
        ">",
        "||",
        "&&",
        "enttype",
        "target>",
        "player",
        "eq",
        "&&"
      ],
      "attrib_mod": [
        {
          "attrib": [
            4
          ],
          "aspect": 32,
          "table": "Melee_PvPDamage",
          "scale": 1.8871
        }
      ]
    },
    {
      "requires": [
        "enttype",
        "target>",
        "player",
        "eq"
      ],
      "attrib_mod": [
        {
          "attrib": [
            4
          ],
          "aspect": 32,
          "table": "Melee_PvPDamage",
          "scale": 1.8871
        }
      ]
    },
    {
      "requires": [
        "kMeter",
        "source>",
        "0",
        ">",
        "enttype",
        "target>",
        "player",
        "eq",
        "&&"
      ],
      "attrib_mod": [
        {
          "attrib": [
            4
          ],
          "aspect": 32,
          "table": "Melee_PvPDamage",
          "scale": 1.8871
        }
      ]
    },
    {
      "tag": [
        "ASTeamCrit"
      ],
      "chance": 0.07,
      "requires": [
        "enttype",
        "target>",
        "critter",
        "eq",
        "kMeter",
        "source>",
        ".9",
        "<",
        "&&"
      ],
      "attrib_mod": [
        {
          "attrib": [
            4
          ],
          "aspect": 32,
          "table": "Melee_Damage",
          "scale": 1.7,
          "flags": [
            4736,
            0
          ]
        }
      ]
    },
    {
      "chance": 0.5,
      "requires": [
        "kMeter",
        "source>",
        "0",
        ">",
        "enttype",
        "target>",
        "critter",
        "eq",
        "&&"
      ],
      "attrib_mod": [
        {
          "attrib": [
            4
          ],
          "aspect": 32,
          "table": "Melee_Damage",
          "scale": 1.7
        }
      ]
    },
    {
      "chance": 0.6,
      "requires": [
        "enttype",
        "target>",
        "player",
        "eq"
      ],
      "attrib_mod": [
        {
          "attrib": [
            328
          ],
          "scale": 0.67,
          "suppress": [
            {
              "event": 29,
              "seconds": 10
            }
          ]
        }
      ]
    },
    {
      "attrib_mod": [
        {
          "attrib": [
            356
          ],
          "aspect": 16,
          "table": "Melee_Slow",
          "scale": 0.1,
          "duration": 10,
          "flags": [
            656,
            0
          ]
        },
        {
          "attrib": [
            188,
            192,
            200
          ],
          "table": "Melee_Slow",
          "scale": 0.2,
          "duration": 15
        },
        {
          "attrib": [
            204
          ],
          "aspect": 16,
          "table": "Melee_Slow",
          "scale": 0.2,
          "duration": 15,
          "flags": [
            656,
            0
          ]
        }
      ]
    },
    {
      "chance": 0.5,
      "requires": [
        "enttype",
        "target>",
        "critter",
        "eq"
      ],
      "attrib_mod": [
        {
          "attrib": [
            272
          ],
          "type": 0,
          "table": "Melee_Immobilize",
          "scale": 10,
          "magnitude": 0.67,
          "flags": [
            1284,
            0
          ]
        }
      ]
    },
    {
      "chance": 0.5,
      "requires": [
        "enttype",
        "target>",
        "player",
        "eq"
      ],
      "attrib_mod": [
        {
          "attrib": [
            272
          ],
          "type": 0,
          "table": "Melee_PvPMez",
          "magnitude": 0.67,
          "suppress": [
            {
              "event": 19
            },
            {
              "event": 20
            },
            {
              "event": 21
            },
            {
              "event": 22
            },
            {
              "event": 23
            }
          ],
          "flags": [
            1284,
            0
          ]
        }
      ]
    },
    {
      "radius_inner": 0,
      "radius_outer": 0,
      "attrib_mod": [
        {
          "attrib": [
            473
          ],
          "aspect": 32,
          "target": 0,
          "stack_type": 1,
          "flags": [
            560,
            0
          ],
          "param": {
            "Power": {
              "power": [
                "Temporary_Powers.Temporary_Powers.Assassins_Focus"
              ]
            }
          }
        }
      ]
    }
  ],
  "strengths_disallowed": [
    348
  ],
  "travel_suppression": 1
}