{
  "crcfull_name": 3022503624,
  "source_file": "DEFS/POWERS/CABAL_CABAL_MAVEN_LT_MOVEMENT.POWERS",
  "source_name": "Cabal.Cabal_Maven_Lt_Movement.Positioning",
  "display_name": "Positioning",
  "display_help": "Longbow Eagles prefer to attack from the air, and will flee if attacked in melee.",
  "display_short_help": "Positioning",
  "display_target_help": "The Longbow Eagle has fled for better positioning.",
  "display_target_short_help": "Positioning",
  "icon_name": "e3brawling.tga",
  "type": 1,
  "effect_area": 2,
  "max_targets_hit": 16,
  "radius": 8,
  "activate_period": 5,
  "ents_auto_hit": [
    19
  ],
  "effects": [
    {
      "attrib_mod": [
        {
          "attrib": [
            260
          ],
          "target": 0,
          "scale": 100,
          "duration": 3,
          "stack_type": 3,
          "flags": [
            112,
            0
          ]
        }
      ]
    }
  ]
}