{
  "crcfull_name": 1869067402,
  "source_file": "DEFS/POWERS/TANKER_MELEE_CLAWS.POWERS",
  "source_name": "Tanker_Melee.Claws.Swipe",
  "display_name": "Swipe",
  "display_help": "Two quick Swipes with your claws. Does minor lethal damage, but has a quick recharge rate. Damage: Minor, Recharge: Very Fast",
  "display_short_help": "Melee, Minor DMG(Lethal)",
  "icon_name": "Claws_ClawsSwipe.tga",
  "attack_types": [
    "Melee",
    "Lethal"
  ],
  "buy_requires": [
    "Tanker_Defense.Shield_Defense",
    "!",
    "Tanker_Defense.Stone_Armor",
    "!",
    "&&"
  ],
  "radius": 4,
  "range": 7,
  "time_to_activate": 0.83,
  "recharge_time": 2.4,
  "endurance_cost": 3.4944,
  "target": 19,
  "boosts_allowed": [
    28,
    23,
    18,
    9,
    5
  ],
  "modes_disallowed": [
    12
  ],
  "effects": [
    {
      "requires": [
        "enttype",
        "target>",
        "critter",
        "eq"
      ],
      "attrib_mod": [
        {
          "attrib": [
            4
          ],
          "aspect": 32,
          "table": "Melee_Damage",
          "scale": 0.83
        }
      ]
    },
    {
      "requires": [
        "enttype",
        "target>",
        "player",
        "eq"
      ],
      "attrib_mod": [
        {
          "attrib": [
            4
          ],
          "aspect": 32,
          "table": "Melee_PvPDamage",
          "scale": 1.077
        }
      ]
    },
    {
      "tag": [
        "FieryEmbrace"
      ],
      "chance": 0,
      "attrib_mod": [
        {
          "attrib": [
            8
          ],
          "aspect": 32,
          "table": "Melee_Damage",
          "scale": 0.3735
        }
      ]
    }
  ],
  "strengths_disallowed": [
    348
  ],
  "anim_main_target_only": true,
  "travel_suppression": 1
}