{
  "crcfull_name": 3575953546,
  "source_file": "DEFS/POWERS/TEMPORARY_POWERS_TEMPORARY_POWERS.POWERS",
  "source_name": "Temporary_Powers.Temporary_Powers.Pet_Arena_HP",
  "free": true,
  "display_name": "Pet Arena HP",
  "display_help": "This power gives entities in the Pet Arena 3 times normal HP.",
  "display_short_help": "3X HP",
  "icon_name": "Invulnerability_DullPain.tga",
  "type": 1,
  "activate_period": 10,
  "ents_auto_hit": [
    1
  ],
  "ents_affected": [
    1
  ],
  "effects": [
    {
      "attrib_mod": [
        {
          "attrib": [
            80
          ],
          "aspect": 8,
          "target": 0,
          "table": "Melee_HealSelf",
          "scale": 30,
          "duration": 10.25,
          "flags": [
            560,
            0
          ]
        }
      ]
    }
  ],
  "max_boosts": 0,
  "attrib_cache": [
    80
  ]
}