{
  "source_file": "DEFS/POWERS/DOMINATOR_ASSAULT_RADIOACTIVE_ASSAULT.POWERSETS",
  "display_name": "Radioactive Assault",
  "display_help": "You are able to harness the power of Radiation to crush your foes at range and in close quarters. Radioactive Assault attacks have a chance to inflict the Contaminated state on a target for a moderate amount of time. Powers that deal greater damage, have a longer recharge time and animation time have a greater chance to inflict Contaminated. Hitting Contaminated targets with Neutrino Bolt, Contaminated Strike, Radiation Siphon, X-Ray Beam, Proton Volley and Devastating Blow cause a portion of that power's damage to also hit nearby foes. Radiation Assault attacks primarily deal smashing and energy damage, but this set is also capable of dealing some toxic damage.",
  "display_short_help": "Radioactive Assault",
  "icon_name": "Radioactive_Assault_set.ico",
  "powers": [
    "Dominator_Assault.Radioactive_Assault.Neutrino_Bolt",
    "Dominator_Assault.Radioactive_Assault.Contaminated_Strike",
    "Dominator_Assault.Radioactive_Assault.X-Ray_Beam",
    "Dominator_Assault.Radioactive_Assault.Electron_Haze",
    "Dominator_Assault.Radioactive_Assault.Fusion",
    "Dominator_Assault.Radioactive_Assault.Radiation_Siphon",
    "Dominator_Assault.Radioactive_Assault.Atom_Smasher",
    "Dominator_Assault.Radioactive_Assault.Proton_Volley",
    "Dominator_Assault.Radioactive_Assault.Devastating_Blow"
  ],
  "available": [
    0,
    1,
    3,
    9,
    15,
    19,
    27,
    34,
    37
  ],
  "aimax_level": [
    0,
    0,
    0,
    0,
    0,
    0,
    0,
    0,
    0
  ],
  "aimin_rank_con": [
    4294957297,
    4294957297,
    4294957297,
    4294957297,
    4294957297,
    4294957297,
    4294957297,
    4294957297,
    4294957297
  ],
  "aimax_rank_con": [
    9999,
    9999,
    9999,
    9999,
    9999,
    9999,
    9999,
    9999,
    9999
  ],
  "min_difficulty": [
    2,
    2,
    2,
    2,
    2,
    2,
    2,
    2,
    2
  ],
  "max_difficulty": [
    9999,
    9999,
    9999,
    9999,
    9999,
    9999,
    9999,
    9999,
    9999
  ]
}