{
  "crcfull_name": 864217083,
  "source_file": "DEFS/POWERS/INSPIRATIONS_SUPER.POWERS",
  "source_name": "Inspirations.Super.Liberate",
  "display_name": "Liberate",
  "display_help": "Frees you from many Sleep, Hold, Immobilization, Disorient, Fear, Confuse and KnockBack effects and boosts your resistance to Repel, Taunt and Placate effects for 90 seconds. This Inspiration can be used even while under such effects.",
  "display_short_help": "Resist Effects",
  "display_target_help": "Frees you from many Sleep, Hold, Immobilization, Disorient, Fear, Confuse and KnockBack effects and boosts your resistance to Repel, Taunt and Placate effects for 90 seconds. This Inspiration can be used even while under such effects.",
  "display_target_short_help": "Resist Effects",
  "display_attacker_hit": "You are now able to Escape from most effects.",
  "icon_name": "Inspiration_resist_sleep_hold_Lvl_4.tga",
  "type": 4,
  "cast_through_hold": true,
  "cast_through_sleep": true,
  "cast_through_stun": true,
  "cast_through_terrorize": true,
  "ents_auto_hit": [
    1
  ],
  "ents_affected": [
    1
  ],
  "modes_disallowed": [
    12,
    13,
    16
  ],
  "effects": [
    {
      "requires": [
        "isPVPMap?",
        "!"
      ],
      "attrib_mod": [
        {
          "attrib": [
            256,
            264,
            268,
            272,
            276,
            280
          ],
          "target": 0,
          "scale": -40,
          "duration": 90,
          "flags": [
            560,
            0
          ]
        }
      ]
    },
    {
      "attrib_mod": [
        {
          "attrib": [
            324,
            328
          ],
          "target": 0,
          "scale": -20,
          "duration": 90,
          "flags": [
            560,
            0
          ]
        },
        {
          "attrib": [
            332
          ],
          "aspect": 24,
          "target": 0,
          "duration": 90,
          "flags": [
            560,
            0
          ]
        },
        {
          "attrib": [
            248,
            252
          ],
          "aspect": 24,
          "target": 0,
          "scale": 0.75,
          "duration": 90,
          "flags": [
            560,
            0
          ]
        }
      ]
    },
    {
      "requires": [
        "isPVPMap?"
      ],
      "attrib_mod": [
        {
          "attrib": [
            256,
            264,
            268,
            272,
            276,
            280
          ],
          "aspect": 24,
          "target": 0,
          "table": "Melee_Res_Boolean",
          "scale": 3,
          "duration": 90,
          "stack_type": 3,
          "flags": [
            560,
            0
          ]
        }
      ]
    }
  ],
  "travel_suppression": 4,
  "cancelable": true
}