{
  "Lore_Boost": {
    "crcfull_name": 1404189564,
    "source_file": "DEFS/POWERS/INCARNATE_GENESIS_SILENT.POWERS",
    "source_name": "Incarnate.Genesis_Silent.Lore_Boost",
    "free": true,
    "display_name": "Lore Boost Common",
    "display_help": "Lore Boost",
    "display_short_help": "Lore Boost",
    "display_target_short_help": "Lore Boost",
    "icon_name": "Incarnate_Interface_Cognitive_Common.tga",
    "type": 5,
    "activate_requires": [
      "isVIP?",
      "isAccountInventoryLoaded?",
      "!",
      "||"
    ],
    "activate_period": 10,
    "ents_auto_hit": [
      1
    ],
    "ents_affected": [
      1
    ],
    "boosts_allowed": [
      39,
      4,
      3,
      2,
      1,
      0
    ],
    "modes_disallowed": [
      12,
      37
    ],
    "effects": [
      {
        "requires": [
          "enttype",
          "target>",
          "critter",
          "eq"
        ],
        "attrib_mod": [
          {
            "attrib": [
              473
            ],
            "target": 0,
            "flags": [
              112,
              0
            ],
            "param": {
              "Power": {
                "power": [
                  "Incarnate.Genesis_Silent.Lore_Data_Boost"
                ]
              }
            }
          }
        ]
      }
    ],
    "max_boosts": 0,
    "do_not_save": true,
    "boost_ignore_effectiveness": true,
    "boost_combinable": false
  },
  "Lore_Boost_2": {
    "crcfull_name": 870237157,
    "source_file": "DEFS/POWERS/INCARNATE_GENESIS_SILENT.POWERS",
    "source_name": "Incarnate.Genesis_Silent.Lore_Boost_2",
    "free": true,
    "display_name": "Lore Boost Uncommon",
    "display_help": "Lore Boost",
    "display_short_help": "Lore Boost",
    "display_target_short_help": "Lore Boost",
    "icon_name": "Incarnate_Interface_Cognitive_Common.tga",
    "type": 5,
    "activate_requires": [
      "isVIP?",
      "isAccountInventoryLoaded?",
      "!",
      "||"
    ],
    "activate_period": 10,
    "ents_auto_hit": [
      1
    ],
    "ents_affected": [
      1
    ],
    "boosts_allowed": [
      39,
      4,
      3,
      2,
      1,
      0
    ],
    "modes_disallowed": [
      12,
      37
    ],
    "effects": [
      {
        "requires": [
          "enttype",
          "target>",
          "critter",
          "eq"
        ],
        "attrib_mod": [
          {
            "attrib": [
              473
            ],
            "target": 0,
            "flags": [
              112,
              0
            ],
            "param": {
              "Power": {
                "power": [
                  "Incarnate.Genesis_Silent.Lore_Data_Boost_2"
                ]
              }
            }
          }
        ]
      }
    ],
    "max_boosts": 0,
    "do_not_save": true,
    "boost_ignore_effectiveness": true,
    "boost_combinable": false
  },
  "Lore_Boost_3": {
    "crcfull_name": 3249881318,
    "source_file": "DEFS/POWERS/INCARNATE_GENESIS_SILENT.POWERS",
    "source_name": "Incarnate.Genesis_Silent.Lore_Boost_3",
    "free": true,
    "display_name": "Lore Boost Rare",
    "display_help": "Lore Boost",
    "display_short_help": "Lore Boost",
    "display_target_short_help": "Lore Boost",
    "icon_name": "Incarnate_Interface_Cognitive_Common.tga",
    "type": 5,
    "activate_requires": [
      "isVIP?",
      "isAccountInventoryLoaded?",
      "!",
      "||"
    ],
    "activate_period": 10,
    "ents_auto_hit": [
      1
    ],
    "ents_affected": [
      1
    ],
    "boosts_allowed": [
      39,
      4,
      3,
      2,
      1,
      0
    ],
    "modes_disallowed": [
      12,
      37
    ],
    "effects": [
      {
        "requires": [
          "enttype",
          "target>",
          "critter",
          "eq"
        ],
        "attrib_mod": [
          {
            "attrib": [
              473
            ],
            "target": 0,
            "flags": [
              112,
              0
            ],
            "param": {
              "Power": {
                "power": [
                  "Incarnate.Genesis_Silent.Lore_Data_Boost_3"
                ]
              }
            }
          }
        ]
      }
    ],
    "max_boosts": 0,
    "do_not_save": true,
    "boost_ignore_effectiveness": true,
    "boost_combinable": false
  },
  "Lore_Boost_4": {
    "crcfull_name": 360653837,
    "source_file": "DEFS/POWERS/INCARNATE_GENESIS_SILENT.POWERS",
    "source_name": "Incarnate.Genesis_Silent.Lore_Boost_4",
    "free": true,
    "display_name": "Lore Boost Very Rare",
    "display_help": "Lore Boost",
    "display_short_help": "Lore Boost",
    "display_target_short_help": "Lore Boost",
    "icon_name": "Incarnate_Interface_Cognitive_Common.tga",
    "type": 5,
    "activate_requires": [
      "isVIP?",
      "isAccountInventoryLoaded?",
      "!",
      "||"
    ],
    "activate_period": 10,
    "ents_auto_hit": [
      1
    ],
    "ents_affected": [
      1
    ],
    "boosts_allowed": [
      39,
      4,
      3,
      2,
      1,
      0
    ],
    "modes_disallowed": [
      12,
      37
    ],
    "effects": [
      {
        "requires": [
          "enttype",
          "target>",
          "critter",
          "eq"
        ],
        "attrib_mod": [
          {
            "attrib": [
              473
            ],
            "target": 0,
            "flags": [
              112,
              0
            ],
            "param": {
              "Power": {
                "power": [
                  "Incarnate.Genesis_Silent.Lore_Data_Boost_4"
                ]
              }
            }
          }
        ]
      }
    ],
    "max_boosts": 0,
    "do_not_save": true,
    "boost_ignore_effectiveness": true,
    "boost_combinable": false
  },
  "Lore_Data_Boost": {
    "crcfull_name": 2927592610,
    "source_file": "DEFS/POWERS/INCARNATE_GENESIS_SILENT.POWERS",
    "source_name": "Incarnate.Genesis_Silent.Lore_Data_Boost",
    "free": true,
    "display_name": "Lore Boost Common",
    "display_help": "This offensive ally has significantly improved combat skills, increasing their damage and Max HP.",
    "display_short_help": "Auto: +DMG(All)",
    "icon_name": "Katana_BuildUp.tga",
    "type": 1,
    "activate_requires": [
      "enttype",
      "char>",
      "critter",
      "eq"
    ],
    "shoot_through_untouchable": true,
    "activate_period": 99999,
    "lifetime": 300,
    "ents_auto_hit": [
      1
    ],
    "ents_affected": [
      1
    ],
    "modes_disallowed": [
      12,
      37
    ],
    "effects": [
      {
        "attrib_mod": [
          {
            "attrib": [
              0,
              4,
              8,
              12,
              16,
              20,
              24,
              36
            ],
            "aspect": 16,
            "application_type": 1,
            "target": 0,
            "scale": 0.025,
            "duration": 999999,
            "stack_type": 3,
            "flags": [
              560,
              0
            ]
          },
          {
            "attrib": [
              80
            ],
            "aspect": 8,
            "application_type": 1,
            "target": 0,
            "scale": 50,
            "duration": 999999,
            "stack_type": 3,
            "flags": [
              560,
              0
            ]
          }
        ]
      }
    ]
  },
  "Lore_Data_Boost_2": {
    "crcfull_name": 269627187,
    "source_file": "DEFS/POWERS/INCARNATE_GENESIS_SILENT.POWERS",
    "source_name": "Incarnate.Genesis_Silent.Lore_Data_Boost_2",
    "free": true,
    "display_name": "Lore Boost Uncommon",
    "display_help": "This offensive ally has significantly improved combat skills, increasing their damage and Max HP.",
    "display_short_help": "Auto: +DMG(All)",
    "icon_name": "Katana_BuildUp.tga",
    "type": 1,
    "activate_requires": [
      "enttype",
      "char>",
      "critter",
      "eq"
    ],
    "target_requires": [
      "enttype",
      "target>",
      "critter",
      "eq"
    ],
    "activate_period": 99999,
    "lifetime": 300,
    "ents_auto_hit": [
      1
    ],
    "ents_affected": [
      1
    ],
    "modes_disallowed": [
      12,
      37
    ],
    "effects": [
      {
        "attrib_mod": [
          {
            "attrib": [
              0,
              4,
              8,
              12,
              16,
              20,
              24,
              36
            ],
            "aspect": 16,
            "application_type": 1,
            "target": 0,
            "scale": 0.05,
            "duration": 999999,
            "stack_type": 3,
            "flags": [
              560,
              0
            ]
          },
          {
            "attrib": [
              80
            ],
            "aspect": 8,
            "application_type": 1,
            "target": 0,
            "scale": 100,
            "duration": 999999,
            "stack_type": 3,
            "flags": [
              560,
              0
            ]
          }
        ]
      }
    ]
  },
  "Lore_Data_Boost_3": {
    "crcfull_name": 3799624752,
    "source_file": "DEFS/POWERS/INCARNATE_GENESIS_SILENT.POWERS",
    "source_name": "Incarnate.Genesis_Silent.Lore_Data_Boost_3",
    "free": true,
    "display_name": "Lore Boost Rare",
    "display_help": "This offensive ally has significantly improved combat skills, increasing their damage and Max HP.",
    "display_short_help": "Auto: +DMG(All)",
    "icon_name": "Katana_BuildUp.tga",
    "type": 1,
    "activate_requires": [
      "enttype",
      "char>",
      "critter",
      "eq"
    ],
    "target_requires": [
      "enttype",
      "target>",
      "critter",
      "eq"
    ],
    "activate_period": 99999,
    "lifetime": 300,
    "ents_auto_hit": [
      1
    ],
    "ents_affected": [
      1
    ],
    "modes_disallowed": [
      12,
      37
    ],
    "effects": [
      {
        "attrib_mod": [
          {
            "attrib": [
              0,
              4,
              8,
              12,
              16,
              20,
              24,
              36
            ],
            "aspect": 16,
            "application_type": 1,
            "target": 0,
            "scale": 0.075,
            "duration": 999999,
            "stack_type": 3,
            "flags": [
              560,
              0
            ]
          },
          {
            "attrib": [
              80
            ],
            "aspect": 8,
            "application_type": 1,
            "target": 0,
            "scale": 150,
            "duration": 999999,
            "stack_type": 3,
            "flags": [
              560,
              0
            ]
          }
        ]
      }
    ]
  },
  "Lore_Data_Boost_4": {
    "crcfull_name": 917752027,
    "source_file": "DEFS/POWERS/INCARNATE_GENESIS_SILENT.POWERS",
    "source_name": "Incarnate.Genesis_Silent.Lore_Data_Boost_4",
    "free": true,
    "display_name": "Lore Boost Very Rare",
    "display_help": "This offensive ally has significantly improved combat skills, increasing their damage and Max HP.",
    "display_short_help": "Auto: +DMG(All)",
    "icon_name": "Katana_BuildUp.tga",
    "type": 1,
    "activate_requires": [
      "enttype",
      "char>",
      "critter",
      "eq"
    ],
    "target_requires": [
      "enttype",
      "target>",
      "critter",
      "eq"
    ],
    "activate_period": 99999,
    "lifetime": 300,
    "ents_auto_hit": [
      1
    ],
    "ents_affected": [
      1
    ],
    "modes_disallowed": [
      12,
      37
    ],
    "effects": [
      {
        "attrib_mod": [
          {
            "attrib": [
              0,
              4,
              8,
              12,
              16,
              20,
              24,
              36
            ],
            "aspect": 16,
            "application_type": 1,
            "target": 0,
            "scale": 0.1,
            "duration": 999999,
            "stack_type": 3,
            "flags": [
              560,
              0
            ]
          },
          {
            "attrib": [
              80
            ],
            "aspect": 8,
            "application_type": 1,
            "target": 0,
            "scale": 200,
            "duration": 999999,
            "stack_type": 3,
            "flags": [
              560,
              0
            ]
          }
        ]
      }
    ]
  },
  "Judgement_Boost": {
    "crcfull_name": 1596408096,
    "source_file": "DEFS/POWERS/INCARNATE_GENESIS_SILENT.POWERS",
    "source_name": "Incarnate.Genesis_Silent.Judgement_Boost",
    "free": true,
    "display_name": "Judgement Boost Common",
    "display_help": "Judgement Boost",
    "display_short_help": "Judgement Boost",
    "display_target_short_help": "Judgement Boost",
    "icon_name": "Incarnate_Interface_Cognitive_Common.tga",
    "type": 5,
    "activate_requires": [
      "isVIP?",
      "isAccountInventoryLoaded?",
      "!",
      "||"
    ],
    "activate_period": 10,
    "ents_auto_hit": [
      1
    ],
    "ents_affected": [
      1
    ],
    "boosts_allowed": [
      37,
      4,
      3,
      2,
      1,
      0
    ],
    "modes_disallowed": [
      12,
      37
    ],
    "effects": [
      {
        "tag": [
          "Damage"
        ],
        "attrib_mod": [
          {
            "attrib": [
              0,
              4,
              8,
              12,
              16,
              20,
              24,
              36
            ],
            "aspect": 16,
            "target": 0,
            "scale": 0.025,
            "flags": [
              2160,
              0
            ]
          }
        ]
      }
    ],
    "max_boosts": 0,
    "do_not_save": true,
    "boost_ignore_effectiveness": true,
    "boost_combinable": false
  },
  "Judgement_Boost_2": {
    "crcfull_name": 988292772,
    "source_file": "DEFS/POWERS/INCARNATE_GENESIS_SILENT.POWERS",
    "source_name": "Incarnate.Genesis_Silent.Judgement_Boost_2",
    "free": true,
    "display_name": "Judgement Boost Uncommon",
    "display_help": "Judgement Boost",
    "display_short_help": "Judgement Boost",
    "display_target_short_help": "Judgement Boost",
    "icon_name": "Incarnate_Interface_Cognitive_Common.tga",
    "type": 5,
    "activate_requires": [
      "isVIP?",
      "isAccountInventoryLoaded?",
      "!",
      "||"
    ],
    "activate_period": 10,
    "ents_auto_hit": [
      1
    ],
    "ents_affected": [
      1
    ],
    "boosts_allowed": [
      37,
      4,
      3,
      2,
      1,
      0
    ],
    "modes_disallowed": [
      12,
      37
    ],
    "effects": [
      {
        "tag": [
          "Damage"
        ],
        "attrib_mod": [
          {
            "attrib": [
              0,
              4,
              8,
              12,
              16,
              20,
              24,
              36
            ],
            "aspect": 16,
            "target": 0,
            "scale": 0.05,
            "flags": [
              2160,
              0
            ]
          }
        ]
      }
    ],
    "max_boosts": 0,
    "do_not_save": true,
    "boost_ignore_effectiveness": true,
    "boost_combinable": false
  },
  "Judgement_Boost_3": {
    "crcfull_name": 3364070823,
    "source_file": "DEFS/POWERS/INCARNATE_GENESIS_SILENT.POWERS",
    "source_name": "Incarnate.Genesis_Silent.Judgement_Boost_3",
    "free": true,
    "display_name": "Judgement Boost Rare",
    "display_help": "Judgement Boost",
    "display_short_help": "Judgement Boost",
    "display_target_short_help": "Judgement Boost",
    "icon_name": "Incarnate_Interface_Cognitive_Common.tga",
    "type": 5,
    "activate_requires": [
      "isVIP?",
      "isAccountInventoryLoaded?",
      "!",
      "||"
    ],
    "activate_period": 10,
    "ents_auto_hit": [
      1
    ],
    "ents_affected": [
      1
    ],
    "boosts_allowed": [
      37,
      4,
      3,
      2,
      1,
      0
    ],
    "modes_disallowed": [
      12,
      37
    ],
    "effects": [
      {
        "tag": [
          "Damage"
        ],
        "attrib_mod": [
          {
            "attrib": [
              0,
              4,
              8,
              12,
              16,
              20,
              24,
              36
            ],
            "aspect": 16,
            "target": 0,
            "scale": 0.075,
            "flags": [
              2160,
              0
            ]
          }
        ]
      }
    ],
    "max_boosts": 0,
    "do_not_save": true,
    "boost_ignore_effectiveness": true,
    "boost_combinable": false
  },
  "Judgement_Boost_4": {
    "crcfull_name": 474595660,
    "source_file": "DEFS/POWERS/INCARNATE_GENESIS_SILENT.POWERS",
    "source_name": "Incarnate.Genesis_Silent.Judgement_Boost_4",
    "free": true,
    "display_name": "Judgement Boost Very Rare",
    "display_help": "Judgement Boost",
    "display_short_help": "Judgement Boost",
    "display_target_short_help": "Judgement Boost",
    "icon_name": "Incarnate_Interface_Cognitive_Common.tga",
    "type": 5,
    "activate_requires": [
      "isVIP?",
      "isAccountInventoryLoaded?",
      "!",
      "||"
    ],
    "activate_period": 10,
    "ents_auto_hit": [
      1
    ],
    "ents_affected": [
      1
    ],
    "boosts_allowed": [
      37,
      4,
      3,
      2,
      1,
      0
    ],
    "modes_disallowed": [
      12,
      37
    ],
    "effects": [
      {
        "tag": [
          "Damage"
        ],
        "attrib_mod": [
          {
            "attrib": [
              0,
              4,
              8,
              12,
              16,
              20,
              24,
              36
            ],
            "aspect": 16,
            "target": 0,
            "scale": 0.1,
            "flags": [
              2160,
              0
            ]
          }
        ]
      }
    ],
    "max_boosts": 0,
    "do_not_save": true,
    "boost_ignore_effectiveness": true,
    "boost_combinable": false
  },
  "Interface_Boost": {
    "crcfull_name": 976465325,
    "source_file": "DEFS/POWERS/INCARNATE_GENESIS_SILENT.POWERS",
    "source_name": "Incarnate.Genesis_Silent.Interface_Boost",
    "free": true,
    "display_name": "Interface Boost Common",
    "display_help": "Interface Boost",
    "display_short_help": "Auto: +Max HP, +Max END",
    "icon_name": "Katana_BuildUp.tga",
    "type": 1,
    "activate_requires": [
      "isVIP?",
      "isAccountInventoryLoaded?",
      "!",
      "||"
    ],
    "activate_period": 10,
    "ents_auto_hit": [
      1
    ],
    "ents_affected": [
      1
    ],
    "modes_disallowed": [
      12,
      37
    ],
    "effects": [
      {
        "attrib_mod": [
          {
            "attrib": [
              80
            ],
            "aspect": 8,
            "target": 0,
            "table": "Melee_HealSelf",
            "scale": 0.25,
            "duration": 10.25,
            "stack_type": 3,
            "flags": [
              560,
              0
            ]
          },
          {
            "attrib": [
              88
            ],
            "aspect": 8,
            "target": 0,
            "scale": 2,
            "duration": 10.25,
            "stack_type": 3,
            "flags": [
              560,
              0
            ]
          }
        ]
      }
    ],
    "do_not_save": true
  },
  "Interface_Boost_2": {
    "crcfull_name": 2942624912,
    "source_file": "DEFS/POWERS/INCARNATE_GENESIS_SILENT.POWERS",
    "source_name": "Incarnate.Genesis_Silent.Interface_Boost_2",
    "free": true,
    "display_name": "Interface Boost Uncommon",
    "display_help": "Interface Boost",
    "display_short_help": "Auto: +Max HP, +Max END",
    "icon_name": "Katana_BuildUp.tga",
    "type": 1,
    "activate_requires": [
      "isVIP?",
      "isAccountInventoryLoaded?",
      "!",
      "||"
    ],
    "activate_period": 10,
    "ents_auto_hit": [
      1
    ],
    "ents_affected": [
      1
    ],
    "modes_disallowed": [
      12,
      37
    ],
    "effects": [
      {
        "attrib_mod": [
          {
            "attrib": [
              80
            ],
            "aspect": 8,
            "target": 0,
            "table": "Melee_HealSelf",
            "scale": 0.5,
            "duration": 10.25,
            "stack_type": 3,
            "flags": [
              560,
              0
            ]
          },
          {
            "attrib": [
              88
            ],
            "aspect": 8,
            "target": 0,
            "scale": 5,
            "duration": 10.25,
            "stack_type": 3,
            "flags": [
              560,
              0
            ]
          }
        ]
      }
    ],
    "do_not_save": true
  },
  "Interface_Boost_3": {
    "crcfull_name": 1561290643,
    "source_file": "DEFS/POWERS/INCARNATE_GENESIS_SILENT.POWERS",
    "source_name": "Incarnate.Genesis_Silent.Interface_Boost_3",
    "free": true,
    "display_name": "Interface Boost Rare",
    "display_help": "Interface Boost",
    "display_short_help": "Auto: +Max HP, +Max END",
    "icon_name": "Katana_BuildUp.tga",
    "type": 1,
    "activate_requires": [
      "isVIP?",
      "isAccountInventoryLoaded?",
      "!",
      "||"
    ],
    "activate_period": 10,
    "ents_auto_hit": [
      1
    ],
    "ents_affected": [
      1
    ],
    "modes_disallowed": [
      12,
      37
    ],
    "effects": [
      {
        "attrib_mod": [
          {
            "attrib": [
              80
            ],
            "aspect": 8,
            "target": 0,
            "table": "Melee_HealSelf",
            "scale": 0.75,
            "duration": 10.25,
            "stack_type": 3,
            "flags": [
              560,
              0
            ]
          },
          {
            "attrib": [
              88
            ],
            "aspect": 8,
            "target": 0,
            "scale": 7,
            "duration": 10.25,
            "stack_type": 3,
            "flags": [
              560,
              0
            ]
          }
        ]
      }
    ],
    "do_not_save": true
  },
  "Interface_Boost_4": {
    "crcfull_name": 2311390072,
    "source_file": "DEFS/POWERS/INCARNATE_GENESIS_SILENT.POWERS",
    "source_name": "Incarnate.Genesis_Silent.Interface_Boost_4",
    "free": true,
    "display_name": "Interface Boost Very Rare",
    "display_help": "Interface Boost",
    "display_short_help": "Auto: +Max HP, +Max END",
    "icon_name": "Katana_BuildUp.tga",
    "type": 1,
    "activate_requires": [
      "isVIP?",
      "isAccountInventoryLoaded?",
      "!",
      "||"
    ],
    "activate_period": 10,
    "ents_auto_hit": [
      1
    ],
    "ents_affected": [
      1
    ],
    "modes_disallowed": [
      12,
      37
    ],
    "effects": [
      {
        "attrib_mod": [
          {
            "attrib": [
              80
            ],
            "aspect": 8,
            "target": 0,
            "table": "Melee_HealSelf",
            "duration": 10.25,
            "stack_type": 3,
            "flags": [
              560,
              0
            ]
          },
          {
            "attrib": [
              88
            ],
            "aspect": 8,
            "target": 0,
            "scale": 10,
            "duration": 10.25,
            "stack_type": 3,
            "flags": [
              560,
              0
            ]
          }
        ]
      }
    ],
    "do_not_save": true
  },
  "Destiny_Boost": {
    "crcfull_name": 182310599,
    "source_file": "DEFS/POWERS/INCARNATE_GENESIS_SILENT.POWERS",
    "source_name": "Incarnate.Genesis_Silent.Destiny_Boost",
    "free": true,
    "display_name": "Destiny Boost Common",
    "display_help": "Destiny Boost",
    "display_short_help": "Destiny Boost",
    "display_target_short_help": "Destiny Boost",
    "icon_name": "Incarnate_Interface_Cognitive_Common.tga",
    "type": 5,
    "activate_requires": [
      "isVIP?",
      "isAccountInventoryLoaded?",
      "!",
      "||"
    ],
    "activate_period": 10,
    "ents_auto_hit": [
      1
    ],
    "ents_affected": [
      1
    ],
    "boosts_allowed": [
      40,
      4,
      3,
      2,
      1,
      0
    ],
    "modes_disallowed": [
      12,
      37
    ],
    "effects": [
      {
        "tag": [
          "Defense"
        ],
        "attrib_mod": [
          {
            "attrib": [
              104,
              108,
              112,
              116,
              120,
              124,
              128,
              132,
              136,
              140,
              144
            ],
            "aspect": 16,
            "target": 0,
            "scale": 0.025,
            "flags": [
              2160,
              0
            ]
          }
        ]
      },
      {
        "attrib_mod": [
          {
            "attrib": [
              80,
              252
            ],
            "aspect": 16,
            "target": 0,
            "scale": 0.025,
            "flags": [
              2160,
              0
            ]
          }
        ]
      },
      {
        "tag": [
          "Heal"
        ],
        "attrib_mod": [
          {
            "attrib": [
              28
            ],
            "aspect": 16,
            "target": 0,
            "scale": 0.025,
            "flags": [
              2160,
              0
            ]
          }
        ]
      },
      {
        "tag": [
          "Endurance"
        ],
        "attrib_mod": [
          {
            "attrib": [
              88
            ],
            "aspect": 16,
            "target": 0,
            "scale": 0.025,
            "flags": [
              2160,
              0
            ]
          }
        ]
      },
      {
        "tag": [
          "Mez"
        ],
        "attrib_mod": [
          {
            "attrib": [
              248,
              256,
              260,
              264,
              268,
              272,
              276,
              280
            ],
            "aspect": 16,
            "target": 0,
            "scale": 0.025,
            "flags": [
              2160,
              0
            ]
          }
        ]
      }
    ],
    "max_boosts": 0,
    "do_not_save": true,
    "boost_ignore_effectiveness": true,
    "boost_combinable": false
  },
  "Destiny_Boost_2": {
    "crcfull_name": 2109275416,
    "source_file": "DEFS/POWERS/INCARNATE_GENESIS_SILENT.POWERS",
    "source_name": "Incarnate.Genesis_Silent.Destiny_Boost_2",
    "free": true,
    "display_name": "Destiny Boost Uncommon",
    "display_help": "Destiny Boost",
    "display_short_help": "Destiny Boost",
    "display_target_short_help": "Destiny Boost",
    "icon_name": "Incarnate_Interface_Cognitive_Common.tga",
    "type": 5,
    "activate_requires": [
      "isVIP?",
      "isAccountInventoryLoaded?",
      "!",
      "||"
    ],
    "activate_period": 10,
    "ents_auto_hit": [
      1
    ],
    "ents_affected": [
      1
    ],
    "boosts_allowed": [
      40,
      4,
      3,
      2,
      1,
      0
    ],
    "modes_disallowed": [
      12,
      37
    ],
    "effects": [
      {
        "tag": [
          "Defense"
        ],
        "attrib_mod": [
          {
            "attrib": [
              104,
              108,
              112,
              116,
              120,
              124,
              128,
              132,
              136,
              140,
              144
            ],
            "aspect": 16,
            "target": 0,
            "scale": 0.05,
            "flags": [
              2160,
              0
            ]
          }
        ]
      },
      {
        "attrib_mod": [
          {
            "attrib": [
              80,
              252
            ],
            "aspect": 16,
            "target": 0,
            "scale": 0.05,
            "flags": [
              2160,
              0
            ]
          }
        ]
      },
      {
        "tag": [
          "Heal"
        ],
        "attrib_mod": [
          {
            "attrib": [
              28
            ],
            "aspect": 16,
            "target": 0,
            "scale": 0.05,
            "flags": [
              2160,
              0
            ]
          }
        ]
      },
      {
        "tag": [
          "Endurance"
        ],
        "attrib_mod": [
          {
            "attrib": [
              88
            ],
            "aspect": 16,
            "target": 0,
            "scale": 0.05,
            "flags": [
              2160,
              0
            ]
          }
        ]
      },
      {
        "tag": [
          "Mez"
        ],
        "attrib_mod": [
          {
            "attrib": [
              248,
              256,
              260,
              264,
              268,
              272,
              276,
              280
            ],
            "aspect": 16,
            "target": 0,
            "scale": 0.05,
            "flags": [
              2160,
              0
            ]
          }
        ]
      }
    ],
    "max_boosts": 0,
    "do_not_save": true,
    "boost_ignore_effectiveness": true,
    "boost_combinable": false
  },
  "Destiny_Boost_3": {
    "crcfull_name": 2413002267,
    "source_file": "DEFS/POWERS/INCARNATE_GENESIS_SILENT.POWERS",
    "source_name": "Incarnate.Genesis_Silent.Destiny_Boost_3",
    "free": true,
    "display_name": "Destiny Boost Rare",
    "display_help": "Destiny Boost",
    "display_short_help": "Destiny Boost",
    "display_target_short_help": "Destiny Boost",
    "icon_name": "Incarnate_Interface_Cognitive_Common.tga",
    "type": 5,
    "activate_requires": [
      "isVIP?",
      "isAccountInventoryLoaded?",
      "!",
      "||"
    ],
    "activate_period": 10,
    "ents_auto_hit": [
      1
    ],
    "ents_affected": [
      1
    ],
    "boosts_allowed": [
      40,
      4,
      3,
      2,
      1,
      0
    ],
    "modes_disallowed": [
      12,
      37
    ],
    "effects": [
      {
        "tag": [
          "Defense"
        ],
        "attrib_mod": [
          {
            "attrib": [
              104,
              108,
              112,
              116,
              120,
              124,
              128,
              132,
              136,
              140,
              144
            ],
            "aspect": 16,
            "target": 0,
            "scale": 0.075,
            "flags": [
              2160,
              0
            ]
          }
        ]
      },
      {
        "attrib_mod": [
          {
            "attrib": [
              80,
              252
            ],
            "aspect": 16,
            "target": 0,
            "scale": 0.075,
            "flags": [
              2160,
              0
            ]
          }
        ]
      },
      {
        "tag": [
          "Heal"
        ],
        "attrib_mod": [
          {
            "attrib": [
              28
            ],
            "aspect": 16,
            "target": 0,
            "scale": 0.075,
            "flags": [
              2160,
              0
            ]
          }
        ]
      },
      {
        "tag": [
          "Endurance"
        ],
        "attrib_mod": [
          {
            "attrib": [
              88
            ],
            "aspect": 16,
            "target": 0,
            "scale": 0.075,
            "flags": [
              2160,
              0
            ]
          }
        ]
      },
      {
        "tag": [
          "Mez"
        ],
        "attrib_mod": [
          {
            "attrib": [
              248,
              256,
              260,
              264,
              268,
              272,
              276,
              280
            ],
            "aspect": 16,
            "target": 0,
            "scale": 0.075,
            "flags": [
              2160,
              0
            ]
          }
        ]
      }
    ],
    "max_boosts": 0,
    "do_not_save": true,
    "boost_ignore_effectiveness": true,
    "boost_combinable": false
  },
  "Destiny_Boost_4": {
    "crcfull_name": 1528371952,
    "source_file": "DEFS/POWERS/INCARNATE_GENESIS_SILENT.POWERS",
    "source_name": "Incarnate.Genesis_Silent.Destiny_Boost_4",
    "free": true,
    "display_name": "Destiny Boost Very Rare",
    "display_help": "Destiny Boost",
    "display_short_help": "Destiny Boost",
    "display_target_short_help": "Destiny Boost",
    "icon_name": "Incarnate_Interface_Cognitive_Common.tga",
    "type": 5,
    "activate_requires": [
      "isVIP?",
      "isAccountInventoryLoaded?",
      "!",
      "||"
    ],
    "activate_period": 10,
    "ents_auto_hit": [
      1
    ],
    "ents_affected": [
      1
    ],
    "boosts_allowed": [
      40,
      4,
      3,
      2,
      1,
      0
    ],
    "modes_disallowed": [
      12,
      37
    ],
    "effects": [
      {
        "tag": [
          "Defense"
        ],
        "attrib_mod": [
          {
            "attrib": [
              104,
              108,
              112,
              116,
              120,
              124,
              128,
              132,
              136,
              140,
              144
            ],
            "aspect": 16,
            "target": 0,
            "scale": 0.1,
            "flags": [
              2160,
              0
            ]
          }
        ]
      },
      {
        "attrib_mod": [
          {
            "attrib": [
              80,
              252
            ],
            "aspect": 16,
            "target": 0,
            "scale": 0.1,
            "flags": [
              2160,
              0
            ]
          }
        ]
      },
      {
        "tag": [
          "Heal"
        ],
        "attrib_mod": [
          {
            "attrib": [
              28
            ],
            "aspect": 16,
            "target": 0,
            "scale": 0.1,
            "flags": [
              2160,
              0
            ]
          }
        ]
      },
      {
        "tag": [
          "Endurance"
        ],
        "attrib_mod": [
          {
            "attrib": [
              88
            ],
            "aspect": 16,
            "target": 0,
            "scale": 0.1,
            "flags": [
              2160,
              0
            ]
          }
        ]
      },
      {
        "tag": [
          "Mez"
        ],
        "attrib_mod": [
          {
            "attrib": [
              248,
              256,
              260,
              264,
              268,
              272,
              276,
              280
            ],
            "aspect": 16,
            "target": 0,
            "scale": 0.1,
            "flags": [
              2160,
              0
            ]
          }
        ]
      }
    ],
    "max_boosts": 0,
    "do_not_save": true,
    "boost_ignore_effectiveness": true,
    "boost_combinable": false
  }
}