{
  "source_file": "DEFS/POWERS/CONTROLLER_BUFF_TRICK_ARROW.POWERSETS",
  "display_name": "Trick Arrow",
  "display_help": "Trick Arrows are tipped with an odd variety of payloads, which if used strategically, can dramatically alter a battle site.",
  "display_short_help": "Trick Arrow",
  "icon_name": "Trick_Arrow_set.ico",
  "costume_keys": [
    "CustomWeapon_Bow"
  ],
  "costume_parts": [
    "Bow_Default"
  ],
  "powers": [
    "Controller_Buff.Trick_Arrow.Entangling_Arrow",
    "Controller_Buff.Trick_Arrow.Flash_Arrow",
    "Controller_Buff.Trick_Arrow.Glue_Arrow",
    "Controller_Buff.Trick_Arrow.Ice_Arrow",
    "Controller_Buff.Trick_Arrow.Poison_Gas_Arrow",
    "Controller_Buff.Trick_Arrow.Acid_Arrow",
    "Controller_Buff.Trick_Arrow.Disruption_Arrow",
    "Controller_Buff.Trick_Arrow.Oil_Slick_Arrow",
    "Controller_Buff.Trick_Arrow.EMP_Arrow"
  ],
  "available": [
    0,
    1,
    3,
    9,
    15,
    19,
    27,
    34,
    37
  ],
  "aimax_level": [
    0,
    0,
    0,
    0,
    0,
    0,
    0,
    0,
    0
  ],
  "aimin_rank_con": [
    4294957297,
    4294957297,
    4294957297,
    4294957297,
    4294957297,
    4294957297,
    4294957297,
    4294957297,
    4294957297
  ],
  "aimax_rank_con": [
    9999,
    9999,
    9999,
    9999,
    9999,
    9999,
    9999,
    9999,
    9999
  ],
  "min_difficulty": [
    2,
    2,
    2,
    2,
    2,
    2,
    2,
    2,
    2
  ],
  "max_difficulty": [
    9999,
    9999,
    9999,
    9999,
    9999,
    9999,
    9999,
    9999,
    9999
  ]
}