{
  "source_file": "DEFS/POWERS/BOOSTS_ATTUNED_SENTINELS_WARD_A.POWERSETS",
  "display_name": "Attuned Sentinels Ward A",
  "display_help": "UNIQUE -- No more than 1 enhancement of this type may be slotted by a character. Enhances the damage of a power by {Boost.Attrib.Damage.Scale}% and accuracy by {Boost.Attrib.Accuracy.Scale}%. This enhancement can only be slotted by Sentinels and may be slotted into any Sentinel damage power.",
  "display_short_help": "Set: Sentinel's Ward",
  "icon_name": "Attuned_Sentinels_Ward_A_set.ico",
  "powers": [
    "Boosts.Attuned_Sentinels_Ward_A.Attuned_Sentinels_Ward_A"
  ]
}