{
  "source_file": "DEFS/POWERS/BOOSTS_ATTUNED_ENTROPIC_CHAOS_D.POWERSETS",
  "display_name": "Attuned Entropic Chaos D",
  "display_help": "Enhances the damage of a power by {Boost.Attrib.Damage.Scale}%, reduces endurance costs by {Boost.Attrib.Endurance.Scale}% and recharge time by {Boost.Attrib.RechargeTime.Scale}%.",
  "display_short_help": "Set: Entropic Chaos",
  "icon_name": "Attuned_Entropic_Chaos_D_set.ico",
  "powers": [
    "Boosts.Attuned_Entropic_Chaos_D.Attuned_Entropic_Chaos_D"
  ]
}