{
  "crcfull_name": 3004027686,
  "source_file": "DEFS/POWERS/MASTERMIND_BUFF_SONIC_RESONANCE.POWERS",
  "source_name": "Mastermind_Buff.Sonic_Resonance.Sonic_Haven",
  "display_name": "Sonic Haven",
  "display_help": "This shield dramatically reduces the damage an ally takes from Fire, Cold, Energy, and Negative Energy attacks for a limited time. You cannot stack multiple Sonic Havens on the same target, however the shield can be improved by another ally using the same power. Can also be used in conjunction with your Sonic Barrier. You cannot use this power on yourself. Recharge: Very Fast",
  "display_short_help": "Ranged, Ally +Res(Fire, Cold, Energy, Negative Energy)",
  "display_target_help": "The Sonic Haven has increased your resistances to Fire, Cold, Energy and Negative Energy damage.",
  "display_target_short_help": "+Res(Fire, Cold, Energy, Negative Energy)",
  "display_attacker_hit": "You protect {PlayerDest} from fire, cold, energy and negative energy attacks with your {PowerName}.",
  "display_victim_hit": "{PlayerSource} protects you from fire, cold, energy and negative energy attacks with a {PowerName}.",
  "icon_name": "SonicDebuff_ProtectElements.tga",
  "ai_report": 1,
  "effect_area": 2,
  "max_targets_hit": 255,
  "radius": 30,
  "range": 80,
  "time_to_activate": 1.33,
  "recharge_time": 2,
  "endurance_cost": 9.75,
  "target": 16,
  "ents_auto_hit": [
    16
  ],
  "ents_affected": [
    16
  ],
  "boosts_allowed": [
    35,
    23,
    22,
    18
  ],
  "modes_disallowed": [
    12
  ],
  "effects": [
    {
      "attrib_mod": [
        {
          "attrib": [
            8,
            12,
            16,
            20
          ],
          "aspect": 24,
          "table": "Ranged_Res_Dmg",
          "scale": 2,
          "duration": 240,
          "stack_type": 3,
          "flags": [
            544,
            0
          ],
          "fx": {
            "continuing_fx": "PFX"
          }
        }
      ]
    }
  ],
  "ignore_strength": true,
  "cancelable": true,
  "attrib_cache": [
    8,
    12,
    16,
    20
  ],
  "visual_fx": "MENU/POWERS/ANIMFX/PLAYERPOWERS/CORRUPTORBUFF_SONICRESONANCE_SONICHAVEN.PFX",
  "attack_bits": [
    20,
    327,
    258,
    681,
    383
  ],
  "initial_attack_bits": [
    20,
    327,
    258,
    681,
    383
  ],
  "attack_fx": "POWERS/SONICRESSONANCE/SONICHAVEN/SONICHAVEN.FX",
  "hit_fx": "POWERS/SONICRESSONANCE/BUFF_HIT.FX",
  "initial_attack_fx": "POWERS/SONICRESSONANCE/SONICHAVEN/SONICHAVEN.FX",
  "continuing_fx": "POWERS/SONICRESSONANCE/SONICHAVEN/SONICHAVEN_CONTINUING.FX",
  "continuing_fx1": "POWERS/SONICRESSONANCE/SONICHAVEN/SONICHAVEN_CONTINUING.FX",
  "mode_bits": [
    20
  ],
  "frames_before_hit": 30,
  "attack_frames": 40,
  "initial_frames_before_hit": 30,
  "custom_fx": [
    {
      "token": "Bright Sonic Resonance",
      "source_file": "MENU/POWERS/ANIMFX/PLAYERPOWERS/CORRUPTORBUFF_SONICRESONANCE_SONICHAVEN.PFX",
      "attack_bits": [
        20,
        327,
        258,
        681,
        383
      ],
      "hit_bits": [],
      "initial_attack_bits": [
        20,
        327,
        258,
        681,
        383
      ],
      "attack_fx": "CUSTOMIZEABLEPOWERS/SONICRESONANCE/SONICHAVEN.FX",
      "hit_fx": "CUSTOMIZEABLEPOWERS/SONICRESONANCE/BUFF_HIT.FX",
      "initial_attack_fx": "CUSTOMIZEABLEPOWERS/SONICRESONANCE/SONICHAVEN.FX",
      "continuing_fx": "CUSTOMIZEABLEPOWERS/SONICRESONANCE/SONICHAVEN_CONTINUING.FX",
      "continuing_fx1": "CUSTOMIZEABLEPOWERS/SONICRESONANCE/SONICHAVEN_CONTINUING.FX",
      "frames_before_hit": 30,
      "attack_frames": 40,
      "initial_frames_before_hit": 30,
      "palette": "Additive"
    },
    {
      "token": "Dark Sonic Resonance",
      "source_file": "MENU/POWERS/ANIMFX/PLAYERPOWERS/CORRUPTORBUFF_SONICRESONANCE_SONICHAVEN.PFX",
      "attack_bits": [
        20,
        327,
        258,
        681,
        383
      ],
      "hit_bits": [],
      "initial_attack_bits": [
        20,
        327,
        258,
        681,
        383
      ],
      "attack_fx": "CUSTOMIZEABLEPOWERS/SONICRESONANCE/SUBTRACTIVE/SONICHAVEN.FX",
      "hit_fx": "CUSTOMIZEABLEPOWERS/SONICRESONANCE/SUBTRACTIVE/BUFF_HIT.FX",
      "initial_attack_fx": "CUSTOMIZEABLEPOWERS/SONICRESONANCE/SUBTRACTIVE/SONICHAVEN.FX",
      "continuing_fx": "CUSTOMIZEABLEPOWERS/SONICRESONANCE/SUBTRACTIVE/SONICHAVEN_CONTINUING.FX",
      "continuing_fx1": "CUSTOMIZEABLEPOWERS/SONICRESONANCE/SUBTRACTIVE/SONICHAVEN_CONTINUING.FX",
      "frames_before_hit": 30,
      "attack_frames": 40,
      "initial_frames_before_hit": 30
    },
    {
      "token": "Bright Sonic DeBuff Alternate",
      "source_file": "MENU/POWERS/ANIMFX/PLAYERPOWERS/CORRUPTORBUFF_SONICRESONANCE_SONICHAVEN.PFX",
      "display_name": "Bright Sonic Haven",
      "attack_bits": [
        20,
        327,
        258,
        681,
        685
      ],
      "hit_bits": [],
      "initial_attack_bits": [
        20,
        327,
        258,
        681,
        685
      ],
      "attack_fx": "CUSTOMIZEABLEPOWERS/SONICRESONANCE/CUSTANIM_SONICHAVEN.FX",
      "hit_fx": "CUSTOMIZEABLEPOWERS/SONICRESONANCE/BUFF_HIT.FX",
      "initial_attack_fx": "CUSTOMIZEABLEPOWERS/SONICRESONANCE/CUSTANIM_SONICHAVEN.FX",
      "continuing_fx": "CUSTOMIZEABLEPOWERS/SONICRESONANCE/SONICHAVEN_CONTINUING.FX",
      "continuing_fx1": "CUSTOMIZEABLEPOWERS/SONICRESONANCE/SONICHAVEN_CONTINUING.FX",
      "frames_before_hit": 30,
      "attack_frames": 40,
      "initial_frames_before_hit": 30,
      "palette": "Additive"
    },
    {
      "token": "Dark Sonic DeBuff Alternate",
      "source_file": "MENU/POWERS/ANIMFX/PLAYERPOWERS/CORRUPTORBUFF_SONICRESONANCE_SONICHAVEN.PFX",
      "display_name": "Dark Sonic Haven",
      "attack_bits": [
        20,
        327,
        258,
        681,
        685
      ],
      "hit_bits": [],
      "initial_attack_bits": [
        20,
        327,
        258,
        681,
        685
      ],
      "attack_fx": "CUSTOMIZEABLEPOWERS/SONICRESONANCE/SUBTRACTIVE/CUSTANIM_SONICHAVEN.FX",
      "hit_fx": "CUSTOMIZEABLEPOWERS/SONICRESONANCE/SUBTRACTIVE/BUFF_HIT.FX",
      "initial_attack_fx": "CUSTOMIZEABLEPOWERS/SONICRESONANCE/SUBTRACTIVE/CUSTANIM_SONICHAVEN.FX",
      "continuing_fx": "CUSTOMIZEABLEPOWERS/SONICRESONANCE/SUBTRACTIVE/SONICHAVEN_CONTINUING.FX",
      "continuing_fx1": "CUSTOMIZEABLEPOWERS/SONICRESONANCE/SUBTRACTIVE/SONICHAVEN_CONTINUING.FX",
      "frames_before_hit": 30,
      "attack_frames": 40,
      "initial_frames_before_hit": 30
    }
  ]
}