{
  "crcfull_name": 2973960347,
  "source_file": "DEFS/POWERS/EPIC_CORRUPTOR_MU_MASTERY.POWERS",
  "source_name": "Epic.Corruptor_Mu_Mastery.Conserve_Power",
  "display_name": "Conserve Power",
  "display_help": "You can focus for a moment to conserve your Endurance. After activating this power, you expend less Endurance on all other powers for a while. You must have one other Mu Mastery power to select this power. You must be level 41 and have Power Sink or Charged Armor before selecting this power. Recharge: Very Long",
  "display_short_help": "Self Endurance Discount",
  "icon_name": "Arachnos_Patron_ConservePower.tga",
  "buy_requires": [
    "SpidersKissPatron",
    "Owned?",
    "TheStingerPatron",
    "Owned?",
    "||",
    "BloodInTheWaterPatron",
    "Owned?",
    "||",
    "MiragePatron",
    "Owned?",
    "||",
    "Epic.Corruptor_Mu_Mastery.Power_Sink",
    "Epic.Corruptor_Mu_Mastery.Charged_Armor",
    "||",
    "&&"
  ],
  "time_to_activate": 1.17,
  "recharge_time": 600,
  "endurance_cost": 9.75,
  "ents_auto_hit": [
    1
  ],
  "ents_affected": [
    1
  ],
  "boosts_allowed": [
    23,
    18
  ],
  "modes_disallowed": [
    12,
    8,
    37
  ],
  "effects": [
    {
      "attrib_mod": [
        {
          "attrib": [
            364
          ],
          "aspect": 16,
          "target": 0,
          "table": "Melee_Stun",
          "duration": 90,
          "flags": [
            560,
            0
          ]
        },
        {
          "attrib": [
            468
          ],
          "target": 0,
          "scale": 0,
          "duration": 90,
          "flags": [
            560,
            0
          ]
        }
      ]
    }
  ],
  "cancelable": true
}