{
  "Generic_Recharge": {
    "crcfull_name": 3137709334,
    "source_file": "DEFS/POWERS/BOOSTS_GENERIC_RECHARGE.POWERS",
    "source_name": "Boosts.Generic_Recharge.Generic_Recharge",
    "display_name": "Training: Recharge Reduction",
    "display_help": "Use this Training to focus your power and decrease the Recharge Time of a power. Increases recharge rate by {Boost.Attrib.RechargeTime.Scale}%.",
    "display_short_help": "Increases Attack Rate",
    "icon_name": "E_ICON_GEN_RECHARGE_01.tga",
    "type": 3,
    "activate_period": 10,
    "ents_auto_hit": [
      1
    ],
    "ents_affected": [
      1
    ],
    "boosts_allowed": [
      18,
      4,
      3,
      2,
      1,
      0
    ],
    "effects": [
      {
        "tag": [
          "rechargetime"
        ],
        "attrib_mod": [
          {
            "attrib": [
              356
            ],
            "aspect": 16,
            "target": 0,
            "scale": 0.0833,
            "duration": 10.25,
            "stack_type": 3,
            "flags": [
              2608,
              0
            ]
          }
        ]
      }
    ],
    "attrib_cache": [
      356
    ]
  }
}