{
  "crcfull_name": 625614726,
  "source_file": "DEFS/POWERS/EPIC_ARCTIC_MASTERY.POWERS",
  "source_name": "Epic.Arctic_Mastery.Ice_Storm",
  "display_name": "Ice Storm",
  "display_help": "Shred your foes with this Ice Storm. This power deals a lot of damage in a large area and can Slow all affected targets movement and attack speed. You must be level 44 and have two other Arctic Mastery Powers before selecting this power. Damage: Minor(DoT), Recharge: Long",
  "display_short_help": "Ranged (Location AoE), Minor DoT(Cold), Foe -Recharge, -SPD",
  "display_target_help": "The Ice Storm is freezing you and reducing your Attack rate and Running speed.",
  "display_target_short_help": "DoT(Cold), -Recharge, -SPD",
  "icon_name": "IceBlast_FreezingRain.tga",
  "buy_requires": [
    "Epic.Arctic_Mastery.Chilblain",
    "Epic.Arctic_Mastery.Block_of_Ice",
    "&&",
    "Epic.Arctic_Mastery.Chilblain",
    "Epic.Arctic_Mastery.Ice_Blast",
    "&&",
    "||",
    "Epic.Arctic_Mastery.Block_of_Ice",
    "Epic.Arctic_Mastery.Ice_Blast",
    "&&",
    "||",
    "Epic.Arctic_Mastery.Chilblain",
    "Epic.Arctic_Mastery.Shiver",
    "&&",
    "||",
    "Epic.Arctic_Mastery.Block_of_Ice",
    "Epic.Arctic_Mastery.Shiver",
    "&&",
    "||"
  ],
  "accuracy": 2,
  "effect_area": 3,
  "range": 60,
  "time_to_activate": 2.03,
  "recharge_time": 120,
  "endurance_cost": 19.5,
  "target": 20,
  "ents_auto_hit": [
    1
  ],
  "ents_affected": [
    1
  ],
  "boosts_allowed": [
    29,
    23,
    22,
    18,
    9
  ],
  "modes_disallowed": [
    12,
    8,
    37
  ],
  "effects": [
    {
      "attrib_mod": [
        {
          "attrib": [
            461
          ],
          "table": "Ranged_Level",
          "duration": 15,
          "flags": [
            640,
            4
          ],
          "param": {
            "EntCreate": {
              "entity_def": "Pets_IceStorm"
            }
          }
        }
      ]
    },
    {
      "tag": [
        "FieryEmbrace"
      ],
      "chance": 0,
      "attrib_mod": [
        {
          "attrib": [
            461
          ],
          "table": "Ranged_Level",
          "duration": 15,
          "flags": [
            640,
            4
          ],
          "param": {
            "EntCreate": {
              "entity_def": "Pets_Embraced_IceStorm"
            }
          }
        }
      ]
    }
  ],
  "travel_suppression": 3,
  "attrib_cache": [
    461
  ],
  "visual_fx": "MENU/POWERS/ANIMFX/PLAYERPOWERS/CORRUPTORRANGED_ICEBLAST_ICESTORM.PFX",
  "attack_bits": [
    20,
    252
  ],
  "initial_attack_bits": [
    20,
    252
  ],
  "attack_fx": "POWERS/COLDCONTROL/CHILLINGHANDS.FX",
  "initial_attack_fx": "POWERS/COLDCONTROL/CHILLINGHANDS.FX",
  "mode_bits": [
    20
  ],
  "frames_before_hit": 25,
  "attack_frames": 61,
  "initial_frames_before_hit": 25,
  "custom_fx": [
    {
      "token": "Color Tintable",
      "alt_theme": [
        "Custom Ice Cast"
      ],
      "source_file": "MENU/POWERS/ANIMFX/PLAYERPOWERS/CORRUPTORRANGED_ICEBLAST_ICESTORM.PFX",
      "attack_bits": [
        20,
        252
      ],
      "hit_bits": [],
      "initial_attack_bits": [
        20,
        252
      ],
      "attack_fx": "CUSTOMIZEABLEPOWERS/ICEBLAST/CHILLINGHANDS.FX",
      "initial_attack_fx": "CUSTOMIZEABLEPOWERS/ICEBLAST/CHILLINGHANDS.FX",
      "frames_before_hit": 25,
      "attack_frames": 61,
      "initial_frames_before_hit": 25,
      "palette": "ice"
    }
  ]
}