{
  "Resistance": {
    "crcfull_name": 1492789150,
    "source_file": "DEFS/POWERS/MISSION_MAKER_PETS_LIONESS.POWERS",
    "source_name": "Mission_Maker_Pets.Lioness.Resistance",
    "display_name": "Resistance",
    "display_help": "Lionesses are resistant to Placate and Confuse effects as well as cold, lethal and smashing damage. They also have a minor amount of defense to Melee, Ranged and AoE attacks.",
    "display_short_help": "Auto: +Res(Placate, Confuse, Taunt, Cold, Lethal, Smash) +Def(Melee, Ranged, AoE)",
    "icon_name": "BeastMastery_PetResistance.tga",
    "type": 1,
    "activate_period": 10,
    "ents_auto_hit": [
      1
    ],
    "ents_affected": [
      1
    ],
    "effects": [
      {
        "attrib_mod": [
          {
            "attrib": [
              104,
              108,
              112
            ],
            "target": 0,
            "table": "Melee_SpeedJumping",
            "scale": 0.05,
            "duration": 10.25,
            "stack_type": 3,
            "flags": [
              544,
              0
            ]
          },
          {
            "attrib": [
              252
            ],
            "target": 0,
            "scale": -4,
            "duration": 10.25,
            "stack_type": 3,
            "flags": [
              560,
              0
            ]
          },
          {
            "attrib": [
              256
            ],
            "aspect": 24,
            "target": 0,
            "scale": 0.5,
            "duration": 10.25,
            "stack_type": 3,
            "flags": [
              560,
              0
            ]
          },
          {
            "attrib": [
              256
            ],
            "target": 0,
            "scale": -2,
            "duration": 10.25,
            "stack_type": 3,
            "flags": [
              560,
              0
            ]
          },
          {
            "attrib": [
              188
            ],
            "target": 0,
            "scale": 0.5,
            "duration": 10.25,
            "stack_type": 3,
            "flags": [
              544,
              0
            ]
          },
          {
            "attrib": [
              0,
              4,
              12
            ],
            "aspect": 24,
            "target": 0,
            "table": "Melee_SpeedJumping",
            "scale": 0.12,
            "duration": 10.3,
            "stack_type": 3,
            "flags": [
              560,
              0
            ]
          },
          {
            "attrib": [
              188,
              192,
              356
            ],
            "aspect": 24,
            "target": 0,
            "scale": 0.25,
            "duration": 10,
            "stack_type": 3,
            "flags": [
              560,
              0
            ]
          }
        ]
      }
    ],
    "ignore_strength": true
  },
  "Claw_Rake": {
    "crcfull_name": 2066260162,
    "source_file": "DEFS/POWERS/MISSION_MAKER_PETS_LIONESS.POWERS",
    "source_name": "Mission_Maker_Pets.Lioness.Claw_Rake",
    "display_name": "Claw Rake",
    "display_help": "The beast swipes their target with their razor sharp claws causing Light Lethal damage and Minor Lethal damage over time. Damage: Light, Recharge: Very Fast",
    "display_short_help": "Melee, Light DMG(Lethal), Foe Minor DoT(Lethal)",
    "display_target_help": "You're bleeding from the Vicious Bite.",
    "display_target_short_help": "Minor DoT(Lethal)",
    "icon_name": "BeastMastery_PetViciousBite.tga",
    "attack_types": [
      "Melee",
      "Lethal"
    ],
    "range": 7,
    "time_to_activate": 1.27,
    "recharge_time": 3,
    "endurance_cost": 4.368,
    "target": 19,
    "boosts_allowed": [
      23,
      9,
      5
    ],
    "modes_disallowed": [
      12
    ],
    "effects": [
      {
        "attrib_mod": [
          {
            "attrib": [
              4
            ],
            "aspect": 32,
            "table": "Melee_Damage",
            "scale": 0.84
          },
          {
            "attrib": [
              4
            ],
            "aspect": 32,
            "table": "Melee_Damage",
            "scale": 0.1,
            "duration": 3.1,
            "delay": 0.5,
            "period": 1,
            "tick_chance": 0.8,
            "flags": [
              644,
              0
            ]
          }
        ]
      }
    ],
    "strengths_disallowed": [
      348
    ]
  },
  "Vicious_Bite": {
    "crcfull_name": 2426368151,
    "source_file": "DEFS/POWERS/MISSION_MAKER_PETS_LIONESS.POWERS",
    "source_name": "Mission_Maker_Pets.Lioness.Vicious_Bite",
    "display_name": "Vicious Bite",
    "display_help": "The beast delivers a quick bite to their target causing Moderate Lethal damage and Minor Lethal damage over time. Damage: Moderate, Recharge: Fast",
    "display_short_help": "Melee, Moderate DMG(Lethal), Foe Minor DoT (Lethal)",
    "display_target_help": "You're bleeding from the Vicious Bite.",
    "display_target_short_help": "Minor DoT(Lethal)",
    "icon_name": "BeastMastery_PetViciousBiteCat.tga",
    "attack_types": [
      "Melee",
      "Lethal"
    ],
    "range": 7,
    "time_to_activate": 1.47,
    "recharge_time": 5,
    "endurance_cost": 6.032,
    "target": 19,
    "boosts_allowed": [
      23,
      9,
      5
    ],
    "modes_disallowed": [
      12
    ],
    "effects": [
      {
        "attrib_mod": [
          {
            "attrib": [
              4
            ],
            "aspect": 32,
            "table": "Melee_Damage",
            "scale": 1.16
          },
          {
            "attrib": [
              4
            ],
            "aspect": 32,
            "table": "Melee_Damage",
            "scale": 0.1,
            "duration": 3.1,
            "delay": 0.5,
            "period": 1,
            "tick_chance": 0.8,
            "flags": [
              644,
              0
            ]
          }
        ]
      }
    ],
    "strengths_disallowed": [
      348
    ],
    "preference_multiplier": 2
  },
  "Super_Leap": {
    "crcfull_name": 794095778,
    "source_file": "DEFS/POWERS/MISSION_MAKER_PETS_LIONESS.POWERS",
    "source_name": "Mission_Maker_Pets.Lioness.Super_Leap",
    "display_name": "Super Leap",
    "display_help": "Beasts can super leap!",
    "display_short_help": "Self Leap",
    "icon_name": "Jump_LongJump.tga",
    "type": 1,
    "recharge_time": 10,
    "ents_auto_hit": [
      1
    ],
    "ents_affected": [
      1
    ],
    "modes_disallowed": [
      12
    ],
    "ai_groups": [
      "kJump"
    ],
    "effects": [
      {
        "attrib_mod": [
          {
            "attrib": [
              204
            ],
            "target": 0,
            "table": "Melee_Leap",
            "duration": 10,
            "stack_type": 3,
            "flags": [
              544,
              0
            ]
          },
          {
            "attrib": [
              200
            ],
            "target": 0,
            "table": "Melee_SpeedJumping",
            "duration": 10,
            "stack_type": 3,
            "flags": [
              544,
              0
            ]
          },
          {
            "attrib": [
              188
            ],
            "target": 0,
            "table": "Melee_SpeedRunning",
            "scale": 0.1,
            "duration": 10.25,
            "stack_type": 3,
            "flags": [
              544,
              0
            ]
          },
          {
            "attrib": [
              208
            ],
            "target": 0,
            "table": "Melee_Control",
            "scale": 10,
            "duration": 10,
            "stack_type": 3,
            "flags": [
              544,
              0
            ]
          },
          {
            "attrib": [
              212
            ],
            "target": 0,
            "table": "Melee_Friction",
            "scale": 10,
            "duration": 10,
            "stack_type": 3,
            "flags": [
              544,
              0
            ]
          }
        ]
      }
    ]
  },
  "Wild_Charge": {
    "crcfull_name": 2653103778,
    "source_file": "DEFS/POWERS/MISSION_MAKER_PETS_LIONESS.POWERS",
    "source_name": "Mission_Maker_Pets.Lioness.Wild_Charge",
    "display_name": "Wild Charge",
    "display_help": "The beast breaks into a sprint that boosts damage dealt for the next few seconds. While Wild Charge is in effect the beast will move much faster than normal and be resistant to slow effects. Recharge: Long",
    "display_short_help": "Self +DMG, +Speed, +Res(Slow, Immobilize)",
    "icon_name": "BeastMastery_PetWildCharge.tga",
    "time_to_activate": 0.6,
    "recharge_time": 90,
    "endurance_cost": 5.2,
    "ents_auto_hit": [
      1
    ],
    "ents_affected": [
      1
    ],
    "modes_disallowed": [
      12
    ],
    "ai_groups": [
      "kBuff"
    ],
    "effects": [
      {
        "attrib_mod": [
          {
            "attrib": [
              188
            ],
            "target": 0,
            "duration": 20,
            "stack_type": 3,
            "flags": [
              544,
              0
            ]
          },
          {
            "attrib": [
              0,
              4,
              8,
              12,
              16,
              20,
              24,
              36
            ],
            "aspect": 16,
            "target": 0,
            "table": "Melee_Buff_Dmg",
            "scale": 3.3,
            "duration": 20,
            "stack_type": 3,
            "flags": [
              560,
              0
            ]
          },
          {
            "attrib": [
              272
            ],
            "target": 0,
            "table": "Melee_Res_Boolean",
            "scale": -50,
            "duration": 20,
            "stack_type": 3,
            "flags": [
              544,
              0
            ]
          },
          {
            "attrib": [
              188,
              192,
              356
            ],
            "aspect": 24,
            "target": 0,
            "scale": 0.75,
            "duration": 20,
            "stack_type": 3,
            "flags": [
              560,
              0
            ]
          }
        ]
      }
    ],
    "strengths_disallowed": [
      356
    ],
    "preference_multiplier": 4
  },
  "Lions_Roar": {
    "crcfull_name": 3835418300,
    "source_file": "DEFS/POWERS/MISSION_MAKER_PETS_LIONESS.POWERS",
    "source_name": "Mission_Maker_Pets.Lioness.Lions_Roar",
    "display_name": "Lion's Roar",
    "display_help": "At the beginning of battle the Lion will let out a terrible roar that bolsters the defense of nearby beasts moderately for a short time. Recharge: Very Long",
    "display_short_help": "Click, Ally Beasts +Def(All)",
    "display_attacker_hit": "{PlayerSource} lets out an howl bolstering the defense of nearby beast allies!",
    "icon_name": "BeastMastery_PetLionsRoar.tga",
    "effect_area": 2,
    "max_targets_hit": 255,
    "radius": 15,
    "time_to_activate": 2,
    "recharge_time": 60,
    "endurance_cost": 13,
    "ents_auto_hit": [
      16,
      1
    ],
    "ents_affected": [
      16,
      1
    ],
    "boosts_allowed": [
      23
    ],
    "modes_disallowed": [
      12
    ],
    "ai_groups": [
      "kBuff"
    ],
    "effects": [
      {
        "requires": [
          "NPCPets_MA_Howler_Wolf",
          "target.VillainName>",
          "NPCPets_MA_Howler_Wolf_Alpha",
          "target.VillainName>",
          "||",
          "NPCPets_MA_Lioness",
          "target.VillainName>",
          "||",
          "NPCPets_MA_Dire_Wolf",
          "target.VillainName>",
          "||"
        ],
        "attrib_mod": [
          {
            "attrib": [
              104,
              108,
              112,
              116,
              120,
              124,
              128,
              132,
              136,
              140,
              144
            ],
            "table": "Ranged_Buff_Def",
            "scale": 0.6,
            "duration": 15,
            "caster_stack_type": 1,
            "stack_type": 3,
            "flags": [
              544,
              0
            ]
          }
        ]
      }
    ],
    "strengths_disallowed": [
      356
    ],
    "preference_multiplier": 4
  },
  "Lick_Wounds": {
    "crcfull_name": 2289978222,
    "source_file": "DEFS/POWERS/MISSION_MAKER_PETS_LIONESS.POWERS",
    "source_name": "Mission_Maker_Pets.Lioness.Lick_Wounds",
    "display_name": "Lick Wounds",
    "display_help": "Should the beast become wounded they will lick their wounds to recover a small amount of health and recover additional health over time. Recharge: Long",
    "display_short_help": "Click, Self Minor Heal, +Regen",
    "icon_name": "BeastMastery_PetLickWounds.tga",
    "time_to_activate": 1.53,
    "recharge_time": 60,
    "endurance_cost": 13,
    "ents_auto_hit": [
      1
    ],
    "ents_affected": [
      1
    ],
    "boosts_allowed": [
      23,
      14
    ],
    "modes_disallowed": [
      12
    ],
    "ai_groups": [
      "kHealSelf"
    ],
    "effects": [
      {
        "attrib_mod": [
          {
            "attrib": [
              28
            ],
            "aspect": 32,
            "table": "Ranged_Heal",
            "scale": 1.33
          },
          {
            "attrib": [
              232
            ],
            "target": 0,
            "table": "Ranged_Ones",
            "scale": 2,
            "duration": 30,
            "stack_type": 3,
            "flags": [
              544,
              0
            ]
          }
        ]
      }
    ],
    "strengths_disallowed": [
      356
    ],
    "preference_multiplier": 5
  },
  "Train_Beasts": {
    "crcfull_name": 2601670292,
    "source_file": "DEFS/POWERS/MISSION_MAKER_PETS_LIONESS.POWERS",
    "source_name": "Mission_Maker_Pets.Lioness.Train_Beasts",
    "display_name": "Train Beasts",
    "display_help": "The Lioness has been trained and now can use Lick Wounds and Train Beasts.",
    "display_short_help": "Train Beasts",
    "icon_name": "BeastMastery_TrainBeasts.tga",
    "type": 1,
    "activate_period": 10,
    "ents_auto_hit": [
      1
    ],
    "ents_affected": [
      1
    ],
    "effects": [
      {
        "attrib_mod": [
          {
            "attrib": [
              320
            ],
            "type": 0,
            "target": 0,
            "scale": 10.25,
            "magnitude": 10,
            "stack_type": 3,
            "flags": [
              1072,
              0
            ]
          }
        ]
      }
    ],
    "show_in_inventory": 0,
    "show_in_manage": false,
    "show_in_info": false
  },
  "Ferocious_Growl": {
    "crcfull_name": 1118428526,
    "source_file": "DEFS/POWERS/MISSION_MAKER_PETS_LIONESS.POWERS",
    "source_name": "Mission_Maker_Pets.Lioness.Ferocious_Growl",
    "display_name": "Ferocious Growl",
    "display_help": "The beast rattles her foes by letting out a ferocious growl. Affected foes will be stunned for a short time. Recharge: Very Long",
    "display_short_help": "PBAoE, Foe Stun",
    "icon_name": "BeastMastery_PetFerociousGrowl.tga",
    "effect_area": 2,
    "max_targets_hit": 6,
    "radius": 15,
    "time_to_activate": 2,
    "recharge_time": 120,
    "endurance_cost": 13,
    "boosts_allowed": [
      23,
      21
    ],
    "modes_disallowed": [
      12
    ],
    "ai_groups": [
      "kDebuff"
    ],
    "effects": [
      {
        "requires": [
          "enttype",
          "target>",
          "critter",
          "eq"
        ],
        "attrib_mod": [
          {
            "attrib": [
              276
            ],
            "type": 0,
            "table": "Ranged_Stun",
            "scale": 8,
            "magnitude": 3,
            "flags": [
              1280,
              0
            ]
          }
        ]
      },
      {
        "requires": [
          "enttype",
          "target>",
          "player",
          "eq"
        ],
        "attrib_mod": [
          {
            "attrib": [
              276
            ],
            "type": 0,
            "table": "Ranged_Ones",
            "scale": 2,
            "magnitude": 3,
            "suppress": [
              {
                "event": 19
              },
              {
                "event": 20
              },
              {
                "event": 21
              },
              {
                "event": 22
              },
              {
                "event": 23
              }
            ],
            "flags": [
              1280,
              0
            ]
          }
        ]
      }
    ],
    "strengths_disallowed": [
      348
    ],
    "preference_multiplier": 4
  },
  "Claw_Swipe": {
    "crcfull_name": 1313369897,
    "source_file": "DEFS/POWERS/MISSION_MAKER_PETS_LIONESS.POWERS",
    "source_name": "Mission_Maker_Pets.Lioness.Claw_Swipe",
    "display_name": "Claw Swipe",
    "display_help": "The beast lashes out with a very wide swipe of its claws striking all foes in front of them causing Moderate Lethal damage and causing Minor Lethal damage over time. Damage: Moderate, Recharge: Slow",
    "display_short_help": "Melee, Moderate DMG(Lethal), Foe Minor DoT(Lethal)",
    "display_target_help": "You are bleeding from the Lioness' Claw Swipe.",
    "display_target_short_help": "Minor DoT(Lethal)",
    "icon_name": "BeastMastery_PetClawSwipe.tga",
    "attack_types": [
      "Melee",
      "Lethal"
    ],
    "effect_area": 1,
    "max_targets_hit": 16,
    "radius": 7,
    "arc": 1.5707964,
    "range": 7,
    "time_to_activate": 2.13,
    "recharge_time": 8,
    "endurance_cost": 8.528,
    "target": 19,
    "boosts_allowed": [
      23,
      9,
      5
    ],
    "modes_disallowed": [
      12
    ],
    "effects": [
      {
        "attrib_mod": [
          {
            "attrib": [
              4
            ],
            "aspect": 32,
            "table": "Melee_Damage",
            "scale": 0.363
          },
          {
            "attrib": [
              4
            ],
            "aspect": 32,
            "table": "Melee_Damage",
            "scale": 0.363,
            "delay": 0.5
          },
          {
            "attrib": [
              4
            ],
            "aspect": 32,
            "table": "Melee_Damage",
            "scale": 0.242
          },
          {
            "attrib": [
              4
            ],
            "aspect": 32,
            "table": "Melee_Damage",
            "scale": 0.242,
            "delay": 0.5
          },
          {
            "attrib": [
              4
            ],
            "aspect": 32,
            "table": "Melee_Damage",
            "scale": 0.125,
            "duration": 3.1,
            "delay": 0.5,
            "period": 1,
            "tick_chance": 0.8,
            "flags": [
              644,
              0
            ]
          }
        ]
      }
    ],
    "max_boosts": 10,
    "strengths_disallowed": [
      348
    ],
    "preference_multiplier": 3
  },
  "Tame_Beasts": {
    "crcfull_name": 3004846596,
    "source_file": "DEFS/POWERS/MISSION_MAKER_PETS_LIONESS.POWERS",
    "source_name": "Mission_Maker_Pets.Lioness.Tame_Beasts",
    "display_name": "Tame Beasts",
    "display_help": "The Lioness has been tamed and can now use Ferocious Growl and Claw Swipe.",
    "display_short_help": "Tame Beasts",
    "icon_name": "BeastMastery_TameBeasts.tga",
    "type": 1,
    "activate_period": 10,
    "ents_auto_hit": [
      1
    ],
    "ents_affected": [
      1
    ],
    "effects": [
      {
        "attrib_mod": [
          {
            "attrib": [
              320
            ],
            "type": 0,
            "target": 0,
            "scale": 10.25,
            "magnitude": 10,
            "stack_type": 3,
            "flags": [
              1072,
              0
            ]
          }
        ]
      }
    ],
    "show_in_inventory": 0,
    "show_in_manage": false,
    "show_in_info": false
  }
}