{
  "crcfull_name": 2601919088,
  "source_file": "DEFS/POWERS/PETS_BLASTER_RADIATION_SNIPE.POWERS",
  "source_name": "Pets.Blaster_Radiation_Snipe.Proton_Volley_Normal",
  "display_name": "Proton Volley",
  "display_help": "Hurls a volley of alpha particles over an extremely long range. Proton Volley can bypass some of a target's defenses and reduce the target's Defense. This is a sniper attack, and is best fired from a distance as it can be interrupted. Damage: Superior, Recharge: Slow",
  "display_short_help": "Sniper, Superior DMG(Energy), Foe -DEF",
  "display_target_help": "The Proton Volley has reduced your Defenses.",
  "display_target_short_help": "-DEF",
  "icon_name": "RadiationBurst_ProtonVolley",
  "attack_types": [
    "Ranged",
    "Energy"
  ],
  "accuracy": 1.2,
  "range": 150,
  "time_to_activate": 3.33,
  "recharge_time": 12,
  "endurance_cost": 14.352,
  "interrupt_time": 2,
  "target": 19,
  "boosts_allowed": [
    32,
    23,
    22,
    18,
    10,
    9,
    5
  ],
  "modes_disallowed": [
    12
  ],
  "effects": [
    {
      "requires": [
        "enttype",
        "target>",
        "critter",
        "eq"
      ],
      "attrib_mod": [
        {
          "attrib": [
            16
          ],
          "aspect": 32,
          "table": "Ranged_Damage",
          "scale": 1.125,
          "duration": 1.6,
          "period": 0.5
        }
      ]
    },
    {
      "attrib_mod": [
        {
          "attrib": [
            184
          ],
          "table": "Ranged_Debuff_Def",
          "scale": 3,
          "duration": 12,
          "flags": [
            644,
            0
          ]
        },
        {
          "attrib": [
            348
          ],
          "aspect": 16,
          "target": 0,
          "table": "Ranged_Ones",
          "scale": 0.5,
          "duration": 10,
          "stack_type": 3,
          "flags": [
            112,
            0
          ]
        }
      ]
    },
    {
      "requires": [
        "enttype",
        "target>",
        "player",
        "eq"
      ],
      "attrib_mod": [
        {
          "attrib": [
            16
          ],
          "aspect": 32,
          "table": "Ranged_PvPDamage",
          "scale": 0.6422,
          "duration": 1.6,
          "period": 0.5
        }
      ]
    },
    {
      "tag": [
        "Defiance"
      ],
      "attrib_mod": [
        {
          "attrib": [
            0,
            4,
            8,
            12,
            16,
            20,
            24,
            36
          ],
          "aspect": 16,
          "type": 3,
          "target": 0,
          "table": "Ranged_Ones",
          "scale": 0,
          "magnitude": 0,
          "duration_expr": [
            "activatetime",
            "power.base>",
            "7.5",
            "+"
          ],
          "magnitude_expr": [
            ".066",
            "activatetime",
            "power.base>",
            "*",
            "areafactor",
            "power.base>",
            "/"
          ],
          "flags": [
            112,
            0
          ]
        }
      ]
    }
  ],
  "travel_suppression": 1
}